WeightedListPicker/WeightedListPicker.py
WeightedListPicker/__init__.py
WeightedListPicker-0.0.1.dist-info/LICENSE
WeightedListPicker-0.0.1.dist-info/METADATA
WeightedListPicker-0.0.1.dist-info/WHEEL
WeightedListPicker-0.0.1.dist-info/top_level.txt
WeightedListPicker-0.0.1.dist-info/RECORD
