Metadata-Version: 2.1
Name: WeightedListPicker
Version: 0.0.1
Summary: A Weighted list picker. throw in two lists, One with any type variable and the other with chances in the form of int variables.
Home-page: https://github.com/SirRolf/WeightedListPicker
Author: SirRolf
Author-email: Flomo123456789@gmail.com
License: UNKNOWN
Platform: UNKNOWN
Classifier: Programming Language :: Python :: 3
Classifier: License :: OSI Approved :: MIT License
Classifier: Operating System :: OS Independent
Requires-Python: >=3.8
